poma_chunker/version.py
poma_chunker/chunker.py
poma_chunker/security.py
poma_chunker/__init__.py
poma_chunker/chunker_core.cpython-313-darwin.so
poma_chunker/retrieval.py
poma_chunker/chunker_core.c
poma_chunker/retrieval_core.c
poma_chunker/retrieval_core.cpython-313-darwin.so
poma_chunker-0.1.3.dist-info/RECORD
poma_chunker-0.1.3.dist-info/WHEEL
poma_chunker-0.1.3.dist-info/top_level.txt
poma_chunker-0.1.3.dist-info/METADATA
poma_chunker-0.1.3.dist-info/licenses/LICENSE.txt
