Metadata-Version: 2.4
Name: poma-chunker
Version: 0.1.3
Summary: Compiled chunking + retrieval engine for .poma documents
Author-email: "TIGON S.L.U." <info@poma.science>
License-Expression: LicenseRef-Proprietary
Requires-Python: >=3.10
License-File: LICENSE.txt
Requires-Dist: litellm
Requires-Dist: pandas
Requires-Dist: tiktoken
Requires-Dist: beautifulsoup4
Requires-Dist: chardet
Dynamic: license-file
